{
"meta":{"test_sets":[],"test_metrics":[],"learn_metrics":[{"best_value":"Min","name":"Logloss"}],"launch_mode":"Train","parameters":"","iteration_count":500,"learn_sets":["learn"],"name":"experiment"},
"iterations":[
{"learn":[0.6479956874],"iteration":0,"passed_time":0.09881443431,"remaining_time":49.30840272},
{"learn":[0.6083314095],"iteration":1,"passed_time":0.1448913586,"remaining_time":36.0779483},
{"learn":[0.5743381679],"iteration":2,"passed_time":0.1874526683,"remaining_time":31.05465871},
{"learn":[0.5426500575],"iteration":3,"passed_time":0.230626054,"remaining_time":28.59763069},
{"learn":[0.5173333431],"iteration":4,"passed_time":0.2735393971,"remaining_time":27.08040031},
{"learn":[0.4926388123],"iteration":5,"passed_time":0.3157552433,"remaining_time":25.9971817},
{"learn":[0.4735007897],"iteration":6,"passed_time":0.3603265628,"remaining_time":25.37728507},
{"learn":[0.4543563125],"iteration":7,"passed_time":0.4070607036,"remaining_time":25.03423327},
{"learn":[0.4385788035],"iteration":8,"passed_time":0.4500797978,"remaining_time":24.55435341},
{"learn":[0.4227486373],"iteration":9,"passed_time":0.4931590425,"remaining_time":24.16479308},
{"learn":[0.4085430982],"iteration":10,"passed_time":0.5364571095,"remaining_time":23.84795696},
{"learn":[0.395395989],"iteration":11,"passed_time":0.5799485983,"remaining_time":23.58457633},
{"learn":[0.3849230984],"iteration":12,"passed_time":0.6233573963,"remaining_time":23.35192708},
{"learn":[0.3755158621],"iteration":13,"passed_time":0.6664722014,"remaining_time":23.13610642},
{"learn":[0.3666409259],"iteration":14,"passed_time":0.7112893333,"remaining_time":22.99835511},
{"learn":[0.3583998327],"iteration":15,"passed_time":0.7582063359,"remaining_time":22.93574166},
{"learn":[0.3508881435],"iteration":16,"passed_time":0.8017581053,"remaining_time":22.77936264},
{"learn":[0.3439995613],"iteration":17,"passed_time":0.8460263418,"remaining_time":22.65470538},
{"learn":[0.3386764524],"iteration":18,"passed_time":0.8899292047,"remaining_time":22.52926039},
{"learn":[0.3318072638],"iteration":19,"passed_time":0.9334580539,"remaining_time":22.40299329},
{"learn":[0.3270629587],"iteration":20,"passed_time":0.9751316748,"remaining_time":22.24228915},
{"learn":[0.3227538397],"iteration":21,"passed_time":1.016950997,"remaining_time":22.09557166},
{"learn":[0.3185085878],"iteration":22,"passed_time":1.058753759,"remaining_time":21.95763231},
{"learn":[0.3140144935],"iteration":23,"passed_time":1.101311669,"remaining_time":21.84268143},
{"learn":[0.3105983262],"iteration":24,"passed_time":1.144509915,"remaining_time":21.74568838},
{"learn":[0.307543146],"iteration":25,"passed_time":1.189326477,"remaining_time":21.68233654},
{"learn":[0.3048318303],"iteration":26,"passed_time":1.231778465,"remaining_time":21.57893386},
{"learn":[0.3020505652],"iteration":27,"passed_time":1.275189823,"remaining_time":21.49605702},
{"learn":[0.2992688866],"iteration":28,"passed_time":1.318014836,"remaining_time":21.40637888},
{"learn":[0.2965111456],"iteration":29,"passed_time":1.360170711,"remaining_time":21.30934114},
{"learn":[0.2940627418],"iteration":30,"passed_time":1.402016514,"remaining_time":21.21115306},
{"learn":[0.2923813668],"iteration":31,"passed_time":1.445878456,"remaining_time":21.14597242},
{"learn":[0.2902709612],"iteration":32,"passed_time":1.490962991,"remaining_time":21.09938536},
{"learn":[0.2882441687],"iteration":33,"passed_time":1.533125057,"remaining_time":21.01283166},
{"learn":[0.2865935123],"iteration":34,"passed_time":1.575505474,"remaining_time":20.93171559},
{"learn":[0.2847513456],"iteration":35,"passed_time":1.61862221,"remaining_time":20.86224181},
{"learn":[0.2832791324],"iteration":36,"passed_time":1.660599233,"remaining_time":20.77993095},
{"learn":[0.2813180929],"iteration":37,"passed_time":1.703013012,"remaining_time":20.70505293},
{"learn":[0.2798086046],"iteration":38,"passed_time":1.745594482,"remaining_time":20.63382195},
{"learn":[0.2781247766],"iteration":39,"passed_time":1.787710387,"remaining_time":20.55866945},
{"learn":[0.2766878411],"iteration":40,"passed_time":1.830008694,"remaining_time":20.4871705},
{"learn":[0.275179181],"iteration":41,"passed_time":1.871447872,"remaining_time":20.40769347},
{"learn":[0.2739565309],"iteration":42,"passed_time":1.913492817,"remaining_time":20.33642366},
{"learn":[0.2726446651],"iteration":43,"passed_time":1.957581982,"remaining_time":20.28766781},
{"learn":[0.2715284667],"iteration":44,"passed_time":2.002706677,"remaining_time":20.24958973},
{"learn":[0.2705428535],"iteration":45,"passed_time":2.045996854,"remaining_time":20.19309938},
{"learn":[0.2694308708],"iteration":46,"passed_time":2.087482323,"remaining_time":20.11977643},
{"learn":[0.2682247429],"iteration":47,"passed_time":2.129289205,"remaining_time":20.05080668},
{"learn":[0.2674299271],"iteration":48,"passed_time":2.172830264,"remaining_time":19.99890712},
{"learn":[0.2665635597],"iteration":49,"passed_time":2.216108271,"remaining_time":19.94497444},
{"learn":[0.2656213682],"iteration":50,"passed_time":2.259373727,"remaining_time":19.89134909},
{"learn":[0.2643866213],"iteration":51,"passed_time":2.301291251,"remaining_time":19.82650924},
{"learn":[0.2633406893],"iteration":52,"passed_time":2.34378885,"remaining_time":19.76742671},
{"learn":[0.262342853],"iteration":53,"passed_time":2.38643573,"remaining_time":19.7101914},
{"learn":[0.2616898305],"iteration":54,"passed_time":2.428086181,"remaining_time":19.64542455},
{"learn":[0.2608672496],"iteration":55,"passed_time":2.471205066,"remaining_time":19.59312588},
{"learn":[0.2598356601],"iteration":56,"passed_time":2.515090289,"remaining_time":19.54710523},
{"learn":[0.2591224016],"iteration":57,"passed_time":2.561567317,"remaining_time":19.52090955},
{"learn":[0.2584008159],"iteration":58,"passed_time":2.605231038,"remaining_time":19.47299809},
{"learn":[0.2576873967],"iteration":59,"passed_time":2.654848437,"remaining_time":19.46888854},
{"learn":[0.2571556724],"iteration":60,"passed_time":2.69679739,"remaining_time":19.40809925},
{"learn":[0.2563406012],"iteration":61,"passed_time":2.73833493,"remaining_time":19.34501128},
{"learn":[0.2555333365],"iteration":62,"passed_time":2.783759518,"remaining_time":19.30956999},
{"learn":[0.254795457],"iteration":63,"passed_time":2.827771722,"remaining_time":19.26419485},
{"learn":[0.2542943689],"iteration":64,"passed_time":2.870698565,"remaining_time":19.21159809},
{"learn":[0.2535999821],"iteration":65,"passed_time":2.912850221,"remaining_time":19.15419691},
{"learn":[0.2531299806],"iteration":66,"passed_time":2.955506111,"remaining_time":19.10050964},
{"learn":[0.2526568894],"iteration":67,"passed_time":2.997831709,"remaining_time":19.0450485},
{"learn":[0.2522304798],"iteration":68,"passed_time":3.040129906,"remaining_time":18.98979695},
{"learn":[0.2515810545],"iteration":69,"passed_time":3.083240041,"remaining_time":18.93990311},
{"learn":[0.2510716484],"iteration":70,"passed_time":3.130720459,"remaining_time":18.91660672},
{"learn":[0.2504160022],"iteration":71,"passed_time":3.174584721,"remaining_time":18.87114251},
{"learn":[0.2500429511],"iteration":72,"passed_time":3.217095571,"remaining_time":18.8178056},
{"learn":[0.2496009026],"iteration":73,"passed_time":3.261097234,"remaining_time":18.77334354},
{"learn":[0.2493032462],"iteration":74,"passed_time":3.304143329,"remaining_time":18.72347886},
{"learn":[0.2489362198],"iteration":75,"passed_time":3.34685974,"remaining_time":18.67195434},
{"learn":[0.2485967846],"iteration":76,"passed_time":3.389108057,"remaining_time":18.61808712},
{"learn":[0.248209722],"iteration":77,"passed_time":3.431099601,"remaining_time":18.56312861},
{"learn":[0.2477748927],"iteration":78,"passed_time":3.473467598,"remaining_time":18.51050454},
{"learn":[0.2474439065],"iteration":79,"passed_time":3.515932457,"remaining_time":18.4586454},
{"learn":[0.2471009955],"iteration":80,"passed_time":3.558249914,"remaining_time":18.40625573},
{"learn":[0.2468785841],"iteration":81,"passed_time":3.600960515,"remaining_time":18.3561158},
{"learn":[0.2466244024],"iteration":82,"passed_time":3.645986929,"remaining_time":18.31778975},
{"learn":[0.2463722302],"iteration":83,"passed_time":3.689294996,"remaining_time":18.27079427},
{"learn":[0.2461030937],"iteration":84,"passed_time":3.73224385,"remaining_time":18.22213174},
{"learn":[0.245685143],"iteration":85,"passed_time":3.775022022,"remaining_time":18.17278043},
{"learn":[0.2454456716],"iteration":86,"passed_time":3.817604392,"remaining_time":18.12265073},
{"learn":[0.2452250048],"iteration":87,"passed_time":3.86110341,"remaining_time":18.07698415},
{"learn":[0.2449348925],"iteration":88,"passed_time":3.903759481,"remaining_time":18.02747356},
{"learn":[0.2446583671],"iteration":89,"passed_time":3.947317401,"remaining_time":17.98222371},
{"learn":[0.2443975307],"iteration":90,"passed_time":3.990157823,"remaining_time":17.93378626},
{"learn":[0.2441027763],"iteration":91,"passed_time":4.033144267,"remaining_time":17.88611805},
{"learn":[0.2439060519],"iteration":92,"passed_time":4.075900418,"remaining_time":17.83754269},
{"learn":[0.2437110474],"iteration":93,"passed_time":4.11971147,"remaining_time":17.79364741},
{"learn":[0.2434887879],"iteration":94,"passed_time":4.162630603,"remaining_time":17.74595152},
{"learn":[0.2431100293],"iteration":95,"passed_time":4.209575746,"remaining_time":17.71529793},
{"learn":[0.2428851849],"iteration":96,"passed_time":4.253016635,"remaining_time":17.66974952},
{"learn":[0.2427240142],"iteration":97,"passed_time":4.296608935,"remaining_time":17.62486522},
{"learn":[0.242573063],"iteration":98,"passed_time":4.339656769,"remaining_time":17.57780166},
{"learn":[0.2423056196],"iteration":99,"passed_time":4.382597462,"remaining_time":17.53038985},
{"learn":[0.2421174351],"iteration":100,"passed_time":4.425259023,"remaining_time":17.48196386},
{"learn":[0.2418502413],"iteration":101,"passed_time":4.467779822,"remaining_time":17.43310166},
{"learn":[0.2415994836],"iteration":102,"passed_time":4.510338062,"remaining_time":17.3845069},
{"learn":[0.2413339526],"iteration":103,"passed_time":4.555501767,"remaining_time":17.34594904},
{"learn":[0.2411352151],"iteration":104,"passed_time":4.597749074,"remaining_time":17.29629413},
{"learn":[0.2409863357],"iteration":105,"passed_time":4.640362974,"remaining_time":17.24814162},
{"learn":[0.2407764069],"iteration":106,"passed_time":4.682994014,"remaining_time":17.20015559},
{"learn":[0.2405033029],"iteration":107,"passed_time":4.728394052,"remaining_time":17.16231915},
{"learn":[0.2402489829],"iteration":108,"passed_time":4.779727208,"remaining_time":17.14562696},
{"learn":[0.2400841951],"iteration":109,"passed_time":4.828670581,"remaining_time":17.11983206},
{"learn":[0.2398623725],"iteration":110,"passed_time":4.873467302,"remaining_time":17.07908811},
{"learn":[0.2396679605],"iteration":111,"passed_time":4.916362925,"remaining_time":17.03168585},
{"learn":[0.2394865424],"iteration":112,"passed_time":4.959175007,"remaining_time":16.98407724},
{"learn":[0.2392925675],"iteration":113,"passed_time":5.001686627,"remaining_time":16.93553542},
{"learn":[0.2391122745],"iteration":114,"passed_time":5.045983733,"remaining_time":16.89307598},
{"learn":[0.2389358745],"iteration":115,"passed_time":5.088861226,"remaining_time":16.84588544},
{"learn":[0.2387027176],"iteration":116,"passed_time":5.13084148,"remaining_time":16.79583151},
{"learn":[0.2385671509],"iteration":117,"passed_time":5.174850294,"remaining_time":16.75248146},
{"learn":[0.2383984537],"iteration":118,"passed_time":5.218188481,"remaining_time":16.7069732},
{"learn":[0.2381729013],"iteration":119,"passed_time":5.262515618,"remaining_time":16.66463279},
{"learn":[0.2379928042],"iteration":120,"passed_time":5.309277809,"remaining_time":16.62988669},
{"learn":[0.2378127511],"iteration":121,"passed_time":5.352830789,"remaining_time":16.58500031},
{"learn":[0.2376171498],"iteration":122,"passed_time":5.395466549,"remaining_time":16.5373243},
{"learn":[0.2374381954],"iteration":123,"passed_time":5.439041979,"remaining_time":16.4925789},
{"learn":[0.2372192642],"iteration":124,"passed_time":5.480832211,"remaining_time":16.44249663},
{"learn":[0.2370616744],"iteration":125,"passed_time":5.523863475,"remaining_time":16.39622968},
{"learn":[0.2369670059],"iteration":126,"passed_time":5.568069631,"remaining_time":16.35346435},
{"learn":[0.2367894444],"iteration":127,"passed_time":5.611977514,"remaining_time":16.30980965},
{"learn":[0.2366574702],"iteration":128,"passed_time":5.655368922,"remaining_time":16.26466566},
{"learn":[0.2364203193],"iteration":129,"passed_time":5.698606898,"remaining_time":16.21911194},
{"learn":[0.2362963059],"iteration":130,"passed_time":5.741528191,"remaining_time":16.17270155},
{"learn":[0.2361083327],"iteration":131,"passed_time":5.783914709,"remaining_time":16.12485313},
{"learn":[0.2358254286],"iteration":132,"passed_time":5.827029554,"remaining_time":16.07909659},
{"learn":[0.2356600269],"iteration":133,"passed_time":5.875732145,"remaining_time":16.04864153},
{"learn":[0.235513047],"iteration":134,"passed_time":5.921095752,"remaining_time":16.00888851},
{"learn":[0.2353824888],"iteration":135,"passed_time":5.96555042,"remaining_time":15.96662024},
{"learn":[0.2351827924],"iteration":136,"passed_time":6.00809335,"remaining_time":15.91925464},
{"learn":[0.2350667745],"iteration":137,"passed_time":6.052087174,"remaining_time":15.8757649},
{"learn":[0.2349382678],"iteration":138,"passed_time":6.094632373,"remaining_time":15.82850566},
{"learn":[0.2347804158],"iteration":139,"passed_time":6.138226883,"remaining_time":15.78401198},
{"learn":[0.2346223693],"iteration":140,"passed_time":6.182885843,"remaining_time":15.74224126},
{"learn":[0.2344438186],"iteration":141,"passed_time":6.225007679,"remaining_time":15.69403344},
{"learn":[0.2342929419],"iteration":142,"passed_time":6.269047043,"remaining_time":15.65069786},
{"learn":[0.2341331932],"iteration":143,"passed_time":6.313815194,"remaining_time":15.60915423},
{"learn":[0.234017541],"iteration":144,"passed_time":6.357264353,"remaining_time":15.56433686},
{"learn":[0.233925465],"iteration":145,"passed_time":6.404139665,"remaining_time":15.52784549},
{"learn":[0.2338269329],"iteration":146,"passed_time":6.448608163,"remaining_time":15.48543321},
{"learn":[0.2336547989],"iteration":147,"passed_time":6.491810699,"remaining_time":15.4399822},
{"learn":[0.2334569943],"iteration":148,"passed_time":6.534700952,"remaining_time":15.39382573},
{"learn":[0.2332579376],"iteration":149,"passed_time":6.577281262,"remaining_time":15.34698961},
{"learn":[0.2331240794],"iteration":150,"passed_time":6.619902722,"remaining_time":15.30030497},
{"learn":[0.2329446523],"iteration":151,"passed_time":6.664526612,"remaining_time":15.2582583},
{"learn":[0.232807745],"iteration":152,"passed_time":6.707370305,"remaining_time":15.21214049},
{"learn":[0.2326708576],"iteration":153,"passed_time":6.749780763,"remaining_time":15.16509184},
{"learn":[0.2325415188],"iteration":154,"passed_time":6.792953788,"remaining_time":15.11980037},
{"learn":[0.2322331925],"iteration":155,"passed_time":6.837101844,"remaining_time":15.07668612},
{"learn":[0.2321298408],"iteration":156,"passed_time":6.877777125,"remaining_time":15.02597168},
{"learn":[0.232017918],"iteration":157,"passed_time":6.923712428,"remaining_time":14.98676994},
{"learn":[0.2319143319],"iteration":158,"passed_time":6.971393948,"remaining_time":14.95122853},
{"learn":[0.2317528894],"iteration":159,"passed_time":7.014093999,"remaining_time":14.90494975},
{"learn":[0.231576887],"iteration":160,"passed_time":7.057546287,"remaining_time":14.86029933},
{"learn":[0.2314878769],"iteration":161,"passed_time":7.10043907,"remaining_time":14.81449633},
{"learn":[0.2312737258],"iteration":162,"passed_time":7.143544715,"remaining_time":14.76916914},
{"learn":[0.2311599185],"iteration":163,"passed_time":7.18766675,"remaining_time":14.72595139},
{"learn":[0.2310654371],"iteration":164,"passed_time":7.231127389,"remaining_time":14.68137985},
{"learn":[0.2309647168],"iteration":165,"passed_time":7.274279514,"remaining_time":14.63620095},
{"learn":[0.2308790405],"iteration":166,"passed_time":7.31744827,"remaining_time":14.59107948},
{"learn":[0.2307253545],"iteration":167,"passed_time":7.359964289,"remaining_time":14.54469133},
{"learn":[0.2306345264],"iteration":168,"passed_time":7.40363241,"remaining_time":14.50060549},
{"learn":[0.2304692336],"iteration":169,"passed_time":7.448018637,"remaining_time":14.45791853},
{"learn":[0.2302992413],"iteration":170,"passed_time":7.495779958,"remaining_time":14.4217053},
{"learn":[0.2302101861],"iteration":171,"passed_time":7.546154525,"remaining_time":14.39034119},
{"learn":[0.2300496183],"iteration":172,"passed_time":7.588876946,"remaining_time":14.34429342},
{"learn":[0.2298888298],"iteration":173,"passed_time":7.631232784,"remaining_time":14.29759705},
{"learn":[0.2297855509],"iteration":174,"passed_time":7.674132377,"remaining_time":14.25196013},
{"learn":[0.2296549845],"iteration":175,"passed_time":7.715726487,"remaining_time":14.20395103},
{"learn":[0.2295672872],"iteration":176,"passed_time":7.758818562,"remaining_time":14.158748},
{"learn":[0.2294749421],"iteration":177,"passed_time":7.801016558,"remaining_time":14.1119513},
{"learn":[0.2293395529],"iteration":178,"passed_time":7.84281791,"remaining_time":14.06449469},
{"learn":[0.2292556884],"iteration":179,"passed_time":7.887124437,"remaining_time":14.02155455},
{"learn":[0.2291074702],"iteration":180,"passed_time":7.933684496,"remaining_time":13.98257102},
{"learn":[0.2289393268],"iteration":181,"passed_time":7.975829562,"remaining_time":13.93579011},
{"learn":[0.2288374519],"iteration":182,"passed_time":8.024016147,"remaining_time":13.89952524},
{"learn":[0.2286687579],"iteration":183,"passed_time":8.070293573,"remaining_time":13.85985201},
{"learn":[0.2285847859],"iteration":184,"passed_time":8.113363438,"remaining_time":13.81464585},
{"learn":[0.2284829374],"iteration":185,"passed_time":8.158415962,"remaining_time":13.77280974},
{"learn":[0.2283863108],"iteration":186,"passed_time":8.20281526,"remaining_time":13.72984586},
{"learn":[0.2282466798],"iteration":187,"passed_time":8.245881484,"remaining_time":13.68465438},
{"learn":[0.2281615332],"iteration":188,"passed_time":8.29008181,"remaining_time":13.64135155},
{"learn":[0.2280666791],"iteration":189,"passed_time":8.331946183,"remaining_time":13.59422798},
{"learn":[0.228005128],"iteration":190,"passed_time":8.376505622,"remaining_time":13.55151957},
{"learn":[0.2279328584],"iteration":191,"passed_time":8.420583797,"remaining_time":13.50801984},
{"learn":[0.2278035769],"iteration":192,"passed_time":8.463780083,"remaining_time":13.46311132},
{"learn":[0.2276751347],"iteration":193,"passed_time":8.506956068,"remaining_time":13.41818844},
{"learn":[0.2275516223],"iteration":194,"passed_time":8.549558859,"remaining_time":13.37238693},
{"learn":[0.227434863],"iteration":195,"passed_time":8.595899305,"remaining_time":13.33241525},
{"learn":[0.2272876044],"iteration":196,"passed_time":8.642734147,"remaining_time":13.29313932},
{"learn":[0.227229882],"iteration":197,"passed_time":8.690624749,"remaining_time":13.25539735},
{"learn":[0.2271084367],"iteration":198,"passed_time":8.73332434,"remaining_time":13.20970164},
{"learn":[0.2270235828],"iteration":199,"passed_time":8.777496106,"remaining_time":13.16624416},
{"learn":[0.2269339218],"iteration":200,"passed_time":8.821368269,"remaining_time":13.12233389},
{"learn":[0.2267682425],"iteration":201,"passed_time":8.86516775,"remaining_time":13.07831678},
{"learn":[0.22662274],"iteration":202,"passed_time":8.909804411,"remaining_time":13.03552665},
{"learn":[0.2265435099],"iteration":203,"passed_time":8.953942656,"remaining_time":12.99199523},
{"learn":[0.2264595041],"iteration":204,"passed_time":8.997096551,"remaining_time":12.94704138},
{"learn":[0.2264036678],"iteration":205,"passed_time":9.041277537,"remaining_time":12.90357085},
{"learn":[0.2262930133],"iteration":206,"passed_time":9.083751836,"remaining_time":12.85767772},
{"learn":[0.2262231242],"iteration":207,"passed_time":9.130276624,"remaining_time":12.81750372},
{"learn":[0.2261545256],"iteration":208,"passed_time":9.176857614,"remaining_time":12.7773472},
{"learn":[0.2260955695],"iteration":209,"passed_time":9.22106511,"remaining_time":12.73385182},
{"learn":[0.2260300454],"iteration":210,"passed_time":9.263993573,"remaining_time":12.68859783},
{"learn":[0.2259050541],"iteration":211,"passed_time":9.306854305,"remaining_time":12.64327377},
{"learn":[0.2257627985],"iteration":212,"passed_time":9.349551546,"remaining_time":12.59775255},
{"learn":[0.2256671502],"iteration":213,"passed_time":9.392161707,"remaining_time":12.55214135},
{"learn":[0.2255780706],"iteration":214,"passed_time":9.433912648,"remaining_time":12.50541909},
{"learn":[0.2254709753],"iteration":215,"passed_time":9.47568123,"remaining_time":12.45876606},
{"learn":[0.2252527925],"iteration":216,"passed_time":9.517057798,"remaining_time":12.41164681},
{"learn":[0.2251682144],"iteration":217,"passed_time":9.559578467,"remaining_time":12.36606022},
{"learn":[0.2250477246],"iteration":218,"passed_time":9.60247015,"remaining_time":12.32097768},
{"learn":[0.2249523078],"iteration":219,"passed_time":9.645547105,"remaining_time":12.27615086},
{"learn":[0.2248525365],"iteration":220,"passed_time":9.690919752,"remaining_time":12.23423806},
{"learn":[0.2247880958],"iteration":221,"passed_time":9.736827805,"remaining_time":12.19296455},
{"learn":[0.2246770852],"iteration":222,"passed_time":9.788525455,"remaining_time":12.15884104},
{"learn":[0.2246071817],"iteration":223,"passed_time":9.8346903,"remaining_time":12.11774341},
{"learn":[0.2245300733],"iteration":224,"passed_time":9.877607813,"remaining_time":12.07263177},
{"learn":[0.2244804406],"iteration":225,"passed_time":9.921579897,"remaining_time":12.0288181},
{"learn":[0.2243735257],"iteration":226,"passed_time":9.965687902,"remaining_time":11.98516651},
{"learn":[0.2242982835],"iteration":227,"passed_time":10.00912577,"remaining_time":11.94071144},
{"learn":[0.2242456317],"iteration":228,"passed_time":10.05233865,"remaining_time":11.89599901},
{"learn":[0.2241656614],"iteration":229,"passed_time":10.09597537,"remaining_time":11.85179717},
{"learn":[0.2240205532],"iteration":230,"passed_time":10.13977462,"remaining_time":11.80778949},
{"learn":[0.2238403463],"iteration":231,"passed_time":10.18186155,"remaining_time":11.76180559},
{"learn":[0.2237102438],"iteration":232,"passed_time":10.2254483,"remaining_time":11.71757381},
{"learn":[0.2236314017],"iteration":233,"passed_time":10.27415566,"remaining_time":11.6791684},
{"learn":[0.2235284529],"iteration":234,"passed_time":10.31932395,"remaining_time":11.63668445},
{"learn":[0.223490359],"iteration":235,"passed_time":10.36245341,"remaining_time":11.59189704},
{"learn":[0.2233701267],"iteration":236,"passed_time":10.40586365,"remaining_time":11.54743519},
{"learn":[0.2232958079],"iteration":237,"passed_time":10.44868837,"remaining_time":11.50233762},
{"learn":[0.2231963484],"iteration":238,"passed_time":10.49162125,"remaining_time":11.45737718},
{"learn":[0.2230691202],"iteration":239,"passed_time":10.53466278,"remaining_time":11.41255135},
{"learn":[0.2229514487],"iteration":240,"passed_time":10.57817163,"remaining_time":11.36824254},
{"learn":[0.2228533839],"iteration":241,"passed_time":10.62169525,"remaining_time":11.32395609},
{"learn":[0.2227692117],"iteration":242,"passed_time":10.66524353,"remaining_time":11.279702},
{"learn":[0.2227203266],"iteration":243,"passed_time":10.70691678,"remaining_time":11.23348646},
{"learn":[0.222664035],"iteration":244,"passed_time":10.75226362,"remaining_time":11.19113152},
{"learn":[0.2225947757],"iteration":245,"passed_time":10.79837828,"remaining_time":11.14954506},
{"learn":[0.2225041931],"iteration":246,"passed_time":10.84397975,"remaining_time":11.10739626},
{"learn":[0.2224142046],"iteration":247,"passed_time":10.8877378,"remaining_time":11.06334648},
{"learn":[0.2223587707],"iteration":248,"passed_time":10.93076317,"remaining_time":11.01856046},
{"learn":[0.2222964791],"iteration":249,"passed_time":10.97344831,"remaining_time":10.97344831},
{"learn":[0.2222094083],"iteration":250,"passed_time":11.01585766,"remaining_time":10.9280819},
{"learn":[0.2220893927],"iteration":251,"passed_time":11.05839669,"remaining_time":10.88286658},
{"learn":[0.2220436334],"iteration":252,"passed_time":11.10213486,"remaining_time":10.83884312},
{"learn":[0.2219629091],"iteration":253,"passed_time":11.14557355,"remaining_time":10.79453186},
{"learn":[0.2218715661],"iteration":254,"passed_time":11.18911776,"remaining_time":10.75032883},
{"learn":[0.2217955373],"iteration":255,"passed_time":11.2290437,"remaining_time":10.70268227},
{"learn":[0.2217240536],"iteration":256,"passed_time":11.27195406,"remaining_time":10.65791765},
{"learn":[0.2216490334],"iteration":257,"passed_time":11.31487549,"remaining_time":10.61317779},
{"learn":[0.2215610941],"iteration":258,"passed_time":11.36914601,"remaining_time":10.57901231},
{"learn":[0.2214901625],"iteration":259,"passed_time":11.41311616,"remaining_time":10.53518415},
{"learn":[0.2213522062],"iteration":260,"passed_time":11.45893931,"remaining_time":10.4930517},
{"learn":[0.2212964612],"iteration":261,"passed_time":11.5013266,"remaining_time":10.44776997},
{"learn":[0.2212132035],"iteration":262,"passed_time":11.54378039,"remaining_time":10.40257016},
{"learn":[0.2211134218],"iteration":263,"passed_time":11.58764727,"remaining_time":10.35865438},
{"learn":[0.2210611595],"iteration":264,"passed_time":11.63051322,"remaining_time":10.31385134},
{"learn":[0.2209582036],"iteration":265,"passed_time":11.67342935,"remaining_time":10.26910702},
{"learn":[0.220905678],"iteration":266,"passed_time":11.71674039,"remaining_time":10.22472101},
{"learn":[0.220835501],"iteration":267,"passed_time":11.76025977,"remaining_time":10.18052338},
{"learn":[0.2207707231],"iteration":268,"passed_time":11.80263782,"remaining_time":10.1353507},
{"learn":[0.2207057968],"iteration":269,"passed_time":11.84583919,"remaining_time":10.09090005},
{"learn":[0.2206097591],"iteration":270,"passed_time":11.88966621,"remaining_time":10.04698732},
{"learn":[0.2205599185],"iteration":271,"passed_time":11.93596351,"remaining_time":10.00514588},
{"learn":[0.2204590947],"iteration":272,"passed_time":11.97884319,"remaining_time":9.960430053},
{"learn":[0.2203597923],"iteration":273,"passed_time":12.02179671,"remaining_time":9.915788531},
{"learn":[0.2203038337],"iteration":274,"passed_time":12.06632747,"remaining_time":9.872449751},
{"learn":[0.2202007308],"iteration":275,"passed_time":12.10940745,"remaining_time":9.827924886},
{"learn":[0.2200866127],"iteration":276,"passed_time":12.15220827,"remaining_time":9.78318572},
{"learn":[0.2200476592],"iteration":277,"passed_time":12.19539789,"remaining_time":9.738770974},
{"learn":[0.2200060458],"iteration":278,"passed_time":12.23910333,"remaining_time":9.694773603},
{"learn":[0.2199221044],"iteration":279,"passed_time":12.27799747,"remaining_time":9.646998013},
{"learn":[0.2198503969],"iteration":280,"passed_time":12.32001746,"remaining_time":9.601721789},
{"learn":[0.2197421911],"iteration":281,"passed_time":12.3624297,"remaining_time":9.556771898},
{"learn":[0.2196555783],"iteration":282,"passed_time":12.40541228,"remaining_time":9.512277259},
{"learn":[0.2195837553],"iteration":283,"passed_time":12.4525545,"remaining_time":9.470956945},
{"learn":[0.2194997444],"iteration":284,"passed_time":12.49881004,"remaining_time":9.428926871},
{"learn":[0.2194270585],"iteration":285,"passed_time":12.54215363,"remaining_time":9.384688377},
{"learn":[0.2193776304],"iteration":286,"passed_time":12.5857836,"remaining_time":9.340668662},
{"learn":[0.2192952208],"iteration":287,"passed_time":12.62862278,"remaining_time":9.296069545},
{"learn":[0.2192140489],"iteration":288,"passed_time":12.67095352,"remaining_time":9.25111139},
{"learn":[0.2191504871],"iteration":289,"passed_time":12.71666801,"remaining_time":9.20862166},
{"learn":[0.2190735413],"iteration":290,"passed_time":12.76035317,"remaining_time":9.164652275},
{"learn":[0.2190101525],"iteration":291,"passed_time":12.80379729,"remaining_time":9.120513135},
{"learn":[0.2189024077],"iteration":292,"passed_time":12.84770174,"remaining_time":9.076703958},
{"learn":[0.2188059562],"iteration":293,"passed_time":12.89457609,"remaining_time":9.034975084},
{"learn":[0.2187307446],"iteration":294,"passed_time":12.93867773,"remaining_time":8.991284521},
{"learn":[0.2186582965],"iteration":295,"passed_time":12.98181191,"remaining_time":8.946924425},
{"learn":[0.2185903449],"iteration":296,"passed_time":13.0303027,"remaining_time":8.906233831},
{"learn":[0.2185157087],"iteration":297,"passed_time":13.07510305,"remaining_time":8.862989316},
{"learn":[0.2184180413],"iteration":298,"passed_time":13.11829795,"remaining_time":8.818655141},
{"learn":[0.2183632329],"iteration":299,"passed_time":13.16091866,"remaining_time":8.773945771},
{"learn":[0.2183125818],"iteration":300,"passed_time":13.20295036,"remaining_time":8.72886087},
{"learn":[0.2182621895],"iteration":301,"passed_time":13.24531993,"remaining_time":8.684017702},
{"learn":[0.218174727],"iteration":302,"passed_time":13.28869253,"remaining_time":8.639842996},
{"learn":[0.2181068068],"iteration":303,"passed_time":13.33106891,"remaining_time":8.595031274},
{"learn":[0.2180507267],"iteration":304,"passed_time":13.37435918,"remaining_time":8.550819804},
{"learn":[0.2180149764],"iteration":305,"passed_time":13.41684941,"remaining_time":8.506107142},
{"learn":[0.2179782298],"iteration":306,"passed_time":13.45869612,"remaining_time":8.461004403},
{"learn":[0.2179418221],"iteration":307,"passed_time":13.4990841,"remaining_time":8.415013465},
{"learn":[0.217860622],"iteration":308,"passed_time":13.54346887,"remaining_time":8.371529301},
{"learn":[0.2177875753],"iteration":309,"passed_time":13.58903089,"remaining_time":8.328760867},
{"learn":[0.2177143103],"iteration":310,"passed_time":13.63155868,"remaining_time":8.284130514},
{"learn":[0.2176745916],"iteration":311,"passed_time":13.67690298,"remaining_time":8.241210772},
{"learn":[0.2176086678],"iteration":312,"passed_time":13.72053022,"remaining_time":8.197249687},
{"learn":[0.2175493222],"iteration":313,"passed_time":13.76442502,"remaining_time":8.153449214},
{"learn":[0.2174684522],"iteration":314,"passed_time":13.80702918,"remaining_time":8.108890152},
{"learn":[0.217421919],"iteration":315,"passed_time":13.85046275,"remaining_time":8.064826409},
{"learn":[0.2173745464],"iteration":316,"passed_time":13.89465351,"remaining_time":8.021203762},
{"learn":[0.2173275077],"iteration":317,"passed_time":13.93618869,"remaining_time":7.976057678},
{"learn":[0.2172904938],"iteration":318,"passed_time":13.97820456,"remaining_time":7.931206979},
{"learn":[0.2172442713],"iteration":319,"passed_time":14.02108694,"remaining_time":7.886861402},
{"learn":[0.2171472699],"iteration":320,"passed_time":14.06365824,"remaining_time":7.842351478},
{"learn":[0.2170715763],"iteration":321,"passed_time":14.10853685,"remaining_time":7.799129066},
{"learn":[0.2169994488],"iteration":322,"passed_time":14.15419018,"remaining_time":7.756320935},
{"learn":[0.2169481021],"iteration":323,"passed_time":14.19752786,"remaining_time":7.712237355},
{"learn":[0.2169282349],"iteration":324,"passed_time":14.24023445,"remaining_time":7.667818549},
{"learn":[0.216891162],"iteration":325,"passed_time":14.28145394,"remaining_time":7.622616523},
{"learn":[0.2168490612],"iteration":326,"passed_time":14.32417931,"remaining_time":7.578235535},
{"learn":[0.2167640192],"iteration":327,"passed_time":14.36574136,"remaining_time":7.533254614},
{"learn":[0.2166662667],"iteration":328,"passed_time":14.40796776,"remaining_time":7.488639779},
{"learn":[0.2166045029],"iteration":329,"passed_time":14.44987601,"remaining_time":7.443875518},
{"learn":[0.2165235279],"iteration":330,"passed_time":14.49253148,"remaining_time":7.399510029},
{"learn":[0.2164476251],"iteration":331,"passed_time":14.53516715,"remaining_time":7.355144821},
{"learn":[0.2163379193],"iteration":332,"passed_time":14.57838716,"remaining_time":7.311083052},
{"learn":[0.2162837658],"iteration":333,"passed_time":14.62173389,"remaining_time":7.267089299},
{"learn":[0.2162340933],"iteration":334,"passed_time":14.6657828,"remaining_time":7.223445262},
{"learn":[0.2161838536],"iteration":335,"passed_time":14.70857518,"remaining_time":7.179185503},
{"learn":[0.2161200764],"iteration":336,"passed_time":14.75110445,"remaining_time":7.134807195},
{"learn":[0.2160387567],"iteration":337,"passed_time":14.79439797,"remaining_time":7.090806129},
{"learn":[0.2159411647],"iteration":338,"passed_time":14.83753681,"remaining_time":7.04673577},
{"learn":[0.2158622203],"iteration":339,"passed_time":14.87999482,"remaining_time":7.002350502},
{"learn":[0.2158093338],"iteration":340,"passed_time":14.92480276,"remaining_time":6.959072254},
{"learn":[0.2157504501],"iteration":341,"passed_time":14.96885035,"remaining_time":6.915433789},
{"learn":[0.2157141982],"iteration":342,"passed_time":15.01293621,"remaining_time":6.871810451},
{"learn":[0.2156711871],"iteration":343,"passed_time":15.05681899,"remaining_time":6.828092333},
{"learn":[0.2156212276],"iteration":344,"passed_time":15.09885373,"remaining_time":6.783542982},
{"learn":[0.2155382517],"iteration":345,"passed_time":15.14259756,"remaining_time":6.739768854},
{"learn":[0.2154855049],"iteration":346,"passed_time":15.18825575,"remaining_time":6.696838989},
{"learn":[0.2154405199],"iteration":347,"passed_time":15.23713213,"remaining_time":6.65529909},
{"learn":[0.2153849459],"iteration":348,"passed_time":15.28770841,"remaining_time":6.614452634},
{"learn":[0.2153151208],"iteration":349,"passed_time":15.33160916,"remaining_time":6.57068964},
{"learn":[0.2152310303],"iteration":350,"passed_time":15.37536845,"remaining_time":6.52686581},
{"learn":[0.2151636851],"iteration":351,"passed_time":15.41803285,"remaining_time":6.482581994},
{"learn":[0.215090581],"iteration":352,"passed_time":15.46303938,"remaining_time":6.439282686},
{"learn":[0.2150510706],"iteration":353,"passed_time":15.50596902,"remaining_time":6.395117166},
{"learn":[0.2149842956],"iteration":354,"passed_time":15.54796364,"remaining_time":6.350576699},
{"learn":[0.2149401481],"iteration":355,"passed_time":15.5902115,"remaining_time":6.306152966},
{"learn":[0.2148629185],"iteration":356,"passed_time":15.63461322,"remaining_time":6.262604174},
{"learn":[0.2147809251],"iteration":357,"passed_time":15.67710056,"remaining_time":6.218291282},
{"learn":[0.2147282927],"iteration":358,"passed_time":15.72060852,"remaining_time":6.174389417},
{"learn":[0.2146707799],"iteration":359,"passed_time":15.76562241,"remaining_time":6.131075381},
{"learn":[0.2145992873],"iteration":360,"passed_time":15.8088128,"remaining_time":6.087049806},
{"learn":[0.2145596536],"iteration":361,"passed_time":15.85202862,"remaining_time":6.043038535},
{"learn":[0.2145138538],"iteration":362,"passed_time":15.89507164,"remaining_time":5.99896643},
{"learn":[0.2144470139],"iteration":363,"passed_time":15.93853957,"remaining_time":5.955058742},
{"learn":[0.2143977067],"iteration":364,"passed_time":15.98124784,"remaining_time":5.910872491},
{"learn":[0.2143559627],"iteration":365,"passed_time":16.02571829,"remaining_time":5.867339484},
{"learn":[0.2142834811],"iteration":366,"passed_time":16.06894542,"remaining_time":5.823350792},
{"learn":[0.2142156708],"iteration":367,"passed_time":16.11147899,"remaining_time":5.779117463},
{"learn":[0.214173926],"iteration":368,"passed_time":16.15541057,"remaining_time":5.735389661},
{"learn":[0.2141064372],"iteration":369,"passed_time":16.20634964,"remaining_time":5.694122848},
{"learn":[0.2140828453],"iteration":370,"passed_time":16.25351853,"remaining_time":5.651492966},
{"learn":[0.2140324844],"iteration":371,"passed_time":16.30030765,"remaining_time":5.608708009},
{"learn":[0.2139996872],"iteration":372,"passed_time":16.34698011,"remaining_time":5.565861861},
{"learn":[0.2139299036],"iteration":373,"passed_time":16.39033256,"remaining_time":5.521876744},
{"learn":[0.2138867924],"iteration":374,"passed_time":16.4325024,"remaining_time":5.477500801},
{"learn":[0.2138031851],"iteration":375,"passed_time":16.47429142,"remaining_time":5.433010999},
{"learn":[0.213747022],"iteration":376,"passed_time":16.51749246,"remaining_time":5.388996214},
{"learn":[0.2136997909],"iteration":377,"passed_time":16.56110074,"remaining_time":5.345117171},
{"learn":[0.2136576493],"iteration":378,"passed_time":16.60421621,"remaining_time":5.301082219},
{"learn":[0.2136227261],"iteration":379,"passed_time":16.64724608,"remaining_time":5.257025078},
{"learn":[0.2135814147],"iteration":380,"passed_time":16.68987074,"remaining_time":5.212846767},
{"learn":[0.2135127575],"iteration":381,"passed_time":16.73152749,"remaining_time":5.168377602},
{"learn":[0.2134512245],"iteration":382,"passed_time":16.77455111,"remaining_time":5.124340678},
{"learn":[0.2134125996],"iteration":383,"passed_time":16.8179108,"remaining_time":5.080410555},
{"learn":[0.2133594402],"iteration":384,"passed_time":16.86786399,"remaining_time":5.038452879},
{"learn":[0.2133041632],"iteration":385,"passed_time":16.91269306,"remaining_time":4.994940437},
{"learn":[0.213273481],"iteration":386,"passed_time":16.95905033,"remaining_time":4.951867408},
{"learn":[0.2132065217],"iteration":387,"passed_time":17.01111634,"remaining_time":4.910425335},
{"learn":[0.2131705411],"iteration":388,"passed_time":17.05376374,"remaining_time":4.866241067},
{"learn":[0.2131353088],"iteration":389,"passed_time":17.09586783,"remaining_time":4.821911438},
{"learn":[0.2130742944],"iteration":390,"passed_time":17.1381833,"remaining_time":4.777652123},
{"learn":[0.2130158868],"iteration":391,"passed_time":17.18107029,"remaining_time":4.733560181},
{"learn":[0.2129681855],"iteration":392,"passed_time":17.22339073,"remaining_time":4.689320123},
{"learn":[0.2129067655],"iteration":393,"passed_time":17.26551388,"remaining_time":4.645036729},
{"learn":[0.2128402025],"iteration":394,"passed_time":17.30778239,"remaining_time":4.600802915},
{"learn":[0.2128075318],"iteration":395,"passed_time":17.352674,"remaining_time":4.557267918},
{"learn":[0.2127437393],"iteration":396,"passed_time":17.39609946,"remaining_time":4.513345703},
{"learn":[0.2126717465],"iteration":397,"passed_time":17.44377309,"remaining_time":4.47051471},
{"learn":[0.2126100557],"iteration":398,"passed_time":17.48480421,"remaining_time":4.425978008},
{"learn":[0.2125592573],"iteration":399,"passed_time":17.52710778,"remaining_time":4.381776944},
{"learn":[0.2125246937],"iteration":400,"passed_time":17.56989387,"remaining_time":4.337704471},
{"learn":[0.2124772581],"iteration":401,"passed_time":17.61350599,"remaining_time":4.293839768},
{"learn":[0.212435591],"iteration":402,"passed_time":17.65768039,"remaining_time":4.250111658},
{"learn":[0.2123595657],"iteration":403,"passed_time":17.70083465,"remaining_time":4.206138927},
{"learn":[0.2123216182],"iteration":404,"passed_time":17.751538,"remaining_time":4.163941012},
{"learn":[0.2122484483],"iteration":405,"passed_time":17.7936607,"remaining_time":4.119714545},
{"learn":[0.2121791393],"iteration":406,"passed_time":17.83598808,"remaining_time":4.075545188},
{"learn":[0.2121141113],"iteration":407,"passed_time":17.8788085,"remaining_time":4.031496035},
{"learn":[0.2120395338],"iteration":408,"passed_time":17.92409838,"remaining_time":3.988002329},
{"learn":[0.2119744408],"iteration":409,"passed_time":17.96956666,"remaining_time":3.944539023},
{"learn":[0.2119262009],"iteration":410,"passed_time":18.01275556,"remaining_time":3.900572371},
{"learn":[0.2118548141],"iteration":411,"passed_time":18.05615413,"remaining_time":3.856654281},
{"learn":[0.2118238794],"iteration":412,"passed_time":18.09955194,"remaining_time":3.812738545},
{"learn":[0.2117575524],"iteration":413,"passed_time":18.14213501,"remaining_time":3.768656065},
{"learn":[0.21171665],"iteration":414,"passed_time":18.19209731,"remaining_time":3.726092221},
{"learn":[0.2116825211],"iteration":415,"passed_time":18.23560288,"remaining_time":3.682189044},
{"learn":[0.2116171648],"iteration":416,"passed_time":18.2791262,"remaining_time":3.638291306},
{"learn":[0.2115595048],"iteration":417,"passed_time":18.32181755,"remaining_time":3.594232152},
{"learn":[0.211522123],"iteration":418,"passed_time":18.36561574,"remaining_time":3.550393497},
{"learn":[0.2114781968],"iteration":419,"passed_time":18.40820907,"remaining_time":3.506325538},
{"learn":[0.2114296345],"iteration":420,"passed_time":18.44988838,"remaining_time":3.462093068},
{"learn":[0.2113762539],"iteration":421,"passed_time":18.49793137,"remaining_time":3.419048926},
{"learn":[0.211303127],"iteration":422,"passed_time":18.54523677,"remaining_time":3.375846882},
{"learn":[0.2112711031],"iteration":423,"passed_time":18.58827916,"remaining_time":3.331861359},
{"learn":[0.2111902758],"iteration":424,"passed_time":18.63520721,"remaining_time":3.288565979},
{"learn":[0.2111475429],"iteration":425,"passed_time":18.68270457,"remaining_time":3.245352437},
{"learn":[0.211102571],"iteration":426,"passed_time":18.72551078,"remaining_time":3.201316832},
{"learn":[0.2110441286],"iteration":427,"passed_time":18.76688017,"remaining_time":3.157045262},
{"learn":[0.2110118843],"iteration":428,"passed_time":18.81012384,"remaining_time":3.113097418},
{"learn":[0.2109607036],"iteration":429,"passed_time":18.85254954,"remaining_time":3.069019692},
{"learn":[0.2109165039],"iteration":430,"passed_time":18.8947584,"remaining_time":3.024914918},
{"learn":[0.2108787328],"iteration":431,"passed_time":18.9447551,"remaining_time":2.982044783},
{"learn":[0.2108031456],"iteration":432,"passed_time":18.98908576,"remaining_time":2.938265002},
{"learn":[0.2107621909],"iteration":433,"passed_time":19.03265243,"remaining_time":2.894366499},
{"learn":[0.2107395954],"iteration":434,"passed_time":19.07701358,"remaining_time":2.850588236},
{"learn":[0.2106740696],"iteration":435,"passed_time":19.11988061,"remaining_time":2.80658798},
{"learn":[0.2106454246],"iteration":436,"passed_time":19.1627185,"remaining_time":2.762588709},
{"learn":[0.2105963577],"iteration":437,"passed_time":19.20658209,"remaining_time":2.71873993},
{"learn":[0.2105585238],"iteration":438,"passed_time":19.25021408,"remaining_time":2.674858904},
{"learn":[0.2105094841],"iteration":439,"passed_time":19.29368422,"remaining_time":2.630956938},
{"learn":[0.2104473191],"iteration":440,"passed_time":19.33676733,"remaining_time":2.587005153},
{"learn":[0.2103921186],"iteration":441,"passed_time":19.37906651,"remaining_time":2.542954429},
{"learn":[0.210350901],"iteration":442,"passed_time":19.42239802,"remaining_time":2.499044441},
{"learn":[0.2103009885],"iteration":443,"passed_time":19.46514163,"remaining_time":2.455062908},
{"learn":[0.2102487503],"iteration":444,"passed_time":19.50837413,"remaining_time":2.411147365},
{"learn":[0.2102048137],"iteration":445,"passed_time":19.5521947,"remaining_time":2.367306085},
{"learn":[0.2101720668],"iteration":446,"passed_time":19.60022183,"remaining_time":2.323963662},
{"learn":[0.2101328934],"iteration":447,"passed_time":19.64613852,"remaining_time":2.280355364},
{"learn":[0.2100796409],"iteration":448,"passed_time":19.68834904,"remaining_time":2.236315815},
{"learn":[0.2100449212],"iteration":449,"passed_time":19.73142664,"remaining_time":2.192380738},
{"learn":[0.2100021497],"iteration":450,"passed_time":19.77411891,"remaining_time":2.148407598},
{"learn":[0.2099572155],"iteration":451,"passed_time":19.81649489,"remaining_time":2.104406537},
{"learn":[0.2099035792],"iteration":452,"passed_time":19.85925046,"remaining_time":2.060452035},
{"learn":[0.2098364298],"iteration":453,"passed_time":19.90249954,"remaining_time":2.016552817},
{"learn":[0.2097994027],"iteration":454,"passed_time":19.94470865,"remaining_time":1.972553603},
{"learn":[0.2097468293],"iteration":455,"passed_time":19.987019,"remaining_time":1.928572009},
{"learn":[0.2097078158],"iteration":456,"passed_time":20.02836886,"remaining_time":1.884507354},
{"learn":[0.2096577855],"iteration":457,"passed_time":20.07117974,"remaining_time":1.840588535},
{"learn":[0.2096123369],"iteration":458,"passed_time":20.11508058,"remaining_time":1.796771904},
{"learn":[0.2095478012],"iteration":459,"passed_time":20.161339,"remaining_time":1.753159913},
{"learn":[0.2095150081],"iteration":460,"passed_time":20.20581327,"remaining_time":1.709385504},
{"learn":[0.2094767545],"iteration":461,"passed_time":20.25087263,"remaining_time":1.665656191},
{"learn":[0.2094286651],"iteration":462,"passed_time":20.29464843,"remaining_time":1.621818557},
{"learn":[0.2093857819],"iteration":463,"passed_time":20.33829857,"remaining_time":1.57797144},
{"learn":[0.2093531361],"iteration":464,"passed_time":20.38233424,"remaining_time":1.53415419},
{"learn":[0.2093151292],"iteration":465,"passed_time":20.42495091,"remaining_time":1.49023247},
{"learn":[0.209245324],"iteration":466,"passed_time":20.46775585,"remaining_time":1.446329643},
{"learn":[0.2092026317],"iteration":467,"passed_time":20.50928833,"remaining_time":1.402344501},
{"learn":[0.2091625739],"iteration":468,"passed_time":20.55233252,"remaining_time":1.35846974},
{"learn":[0.209113825],"iteration":469,"passed_time":20.59594438,"remaining_time":1.314634747},
{"learn":[0.2090769241],"iteration":470,"passed_time":20.63868821,"remaining_time":1.270747257},
{"learn":[0.2090351589],"iteration":471,"passed_time":20.68335725,"remaining_time":1.22697882},
{"learn":[0.209005697],"iteration":472,"passed_time":20.72826554,"remaining_time":1.183220232},
{"learn":[0.2089498084],"iteration":473,"passed_time":20.77027764,"remaining_time":1.13929793},
{"learn":[0.2089123883],"iteration":474,"passed_time":20.81481647,"remaining_time":1.095516657},
{"learn":[0.2088707709],"iteration":475,"passed_time":20.85880439,"remaining_time":1.051704423},
{"learn":[0.2088265192],"iteration":476,"passed_time":20.90083821,"remaining_time":1.00779723},
{"learn":[0.2087247815],"iteration":477,"passed_time":20.94290991,"remaining_time":0.9638996191},
{"learn":[0.2086802708],"iteration":478,"passed_time":20.99115896,"remaining_time":0.9202804556},
{"learn":[0.208637491],"iteration":479,"passed_time":21.03466797,"remaining_time":0.8764444988},
{"learn":[0.2085795683],"iteration":480,"passed_time":21.07807154,"remaining_time":0.8326057365},
{"learn":[0.2085561623],"iteration":481,"passed_time":21.12122163,"remaining_time":0.7887593142},
{"learn":[0.2085275985],"iteration":482,"passed_time":21.16376061,"remaining_time":0.7448942659},
{"learn":[0.208470625],"iteration":483,"passed_time":21.2074731,"remaining_time":0.7010734908},
{"learn":[0.2084409727],"iteration":484,"passed_time":21.25559946,"remaining_time":0.657389674},
{"learn":[0.2083939823],"iteration":485,"passed_time":21.29880853,"remaining_time":0.6135459246},
{"learn":[0.2083281186],"iteration":486,"passed_time":21.34194916,"remaining_time":0.569702955},
{"learn":[0.2082569605],"iteration":487,"passed_time":21.38543234,"remaining_time":0.5258712871},
{"learn":[0.2081879232],"iteration":488,"passed_time":21.42725208,"remaining_time":0.4820036256},
{"learn":[0.2081391787],"iteration":489,"passed_time":21.4707581,"remaining_time":0.4381787368},
{"learn":[0.2081066556],"iteration":490,"passed_time":21.5130354,"remaining_time":0.3943326244},
{"learn":[0.2080700444],"iteration":491,"passed_time":21.55641164,"remaining_time":0.3505107583},
{"learn":[0.2080154392],"iteration":492,"passed_time":21.59945759,"remaining_time":0.3066860104},
{"learn":[0.207972724],"iteration":493,"passed_time":21.64348131,"remaining_time":0.2628762913},
{"learn":[0.2079186852],"iteration":494,"passed_time":21.68883349,"remaining_time":0.2190791262},
{"learn":[0.2078983023],"iteration":495,"passed_time":21.73153914,"remaining_time":0.1752543479},
{"learn":[0.2078537992],"iteration":496,"passed_time":21.77583757,"remaining_time":0.1314436875},
{"learn":[0.2078014632],"iteration":497,"passed_time":21.82035287,"remaining_time":0.08763193923},
{"learn":[0.2077500092],"iteration":498,"passed_time":21.86405006,"remaining_time":0.04381573158},
{"learn":[0.2077031095],"iteration":499,"passed_time":21.90651858,"remaining_time":0}
]}